cli/__init__.py
cli/commands/__init__.py
cli/commands/configure.py
cli/commands/context.py
cli/commands/execute.py
cli/config.py
cli/errors.py
cli/formatters.py
cli/main.py
cli/upsolver/__init__.py
cli/upsolver/api.py
cli/upsolver/api_utils.py
cli/upsolver/auth.py
cli/upsolver/auth_filler.py
cli/upsolver/entities.py
cli/upsolver/poller.py
cli/upsolver/query.py
cli/upsolver/requester.py
cli/upsolver/response.py
cli/utils.py
upsolver_cli-0.6.4.dist-info/entry_points.txt
upsolver_cli-0.6.4.dist-info/METADATA
upsolver_cli-0.6.4.dist-info/LICENSE
upsolver_cli-0.6.4.dist-info/WHEEL
upsolver_cli-0.6.4.dist-info/RECORD
