Metadata-Version: 2.1
Name: upsolver-cli
Version: 0.6.4
Summary: Upsolver's CLI
Home-page: https://github.com/upsolver/cli
License: MIT
Author: alexyavo
Author-email: alex@upsolver.com
Requires-Python: >=3.8,<4.0
Classifier: License :: OSI Approved :: MIT License
Classifier: Programming Language :: Python :: 3
Classifier: Programming Language :: Python :: 3.8
Classifier: Programming Language :: Python :: 3.9
Classifier: Programming Language :: Python :: 3.10
Classifier: Programming Language :: Python :: 3.11
Requires-Dist: click (>=8.0.3,<9.0.0)
Requires-Dist: requests (>=2.27.1,<3.0.0)
Requires-Dist: tabulate (>=0.8.9,<0.9.0)
Requires-Dist: yarl (>=1.7.2,<2.0.0)
Project-URL: Repository, https://github.com/upsolver/cli
